bs/__init__.py
bs/__main__.py
bs/abc.py
bs/battles.py
bs/client.py
bs/clubs.py
bs/errors.py
bs/http.py
bs/login.py
bs/players.py
bs/utils.py
bs.py-1.0.0.dist-info/LICENSE
bs.py-1.0.0.dist-info/METADATA
bs.py-1.0.0.dist-info/WHEEL
bs.py-1.0.0.dist-info/top_level.txt
bs.py-1.0.0.dist-info/RECORD
